ansys/mapdl/reader/_cellqual.cpython-313-darwin.so
ansys/mapdl/reader/misc.py
ansys/mapdl/reader/emat.py
ansys/mapdl/reader/_archive.cpython-313-darwin.so
ansys/mapdl/reader/_version.py
ansys/mapdl/reader/_rst_keys.py
ansys/mapdl/reader/_mp_keys.py
ansys/mapdl/reader/elements.py
ansys/mapdl/reader/plotting.py
ansys/mapdl/reader/__init__.py
ansys/mapdl/reader/mesh.py
ansys/mapdl/reader/full.py
ansys/mapdl/reader/common.py
ansys/mapdl/reader/cyclic_reader.py
ansys/mapdl/reader/_binary_reader.cpython-313-darwin.so
ansys/mapdl/reader/archive.py
ansys/mapdl/reader/errors.py
ansys/mapdl/reader/_relaxmidside.cpython-313-darwin.so
ansys/mapdl/reader/dis_result.py
ansys/mapdl/reader/cell_quality.py
ansys/mapdl/reader/rst.py
ansys/mapdl/reader/_reader.cpython-313-darwin.so
ansys/mapdl/reader/rst_avail.py
ansys/mapdl/reader/examples/TetBeam.cdb
ansys/mapdl/reader/examples/HexBeam.cdb
ansys/mapdl/reader/examples/__init__.py
ansys/mapdl/reader/examples/file.rst
ansys/mapdl/reader/examples/downloads.py
ansys/mapdl/reader/examples/examples.py
ansys/mapdl/reader/examples/file.full
ansys/mapdl/reader/examples/sector.cdb
ansys_mapdl_reader-0.55.1.dist-info/RECORD
ansys_mapdl_reader-0.55.1.dist-info/WHEEL
ansys_mapdl_reader-0.55.1.dist-info/top_level.txt
ansys_mapdl_reader-0.55.1.dist-info/METADATA
ansys_mapdl_reader-0.55.1.dist-info/licenses/LICENSE
ansys_mapdl_reader-0.55.1.dist-info/licenses/AUTHORS
