Metadata-Version: 2.4
Name: ansys-mapdl-reader
Version: 0.55.1
Summary: Pythonic interface to files generated by MAPDL
Home-page: https://github.com/pyansys/pymapdl-reader
Author: Ansys, Inc.
Author-email: pyansys.maintainers@ansys.com
Maintainer: PyAnsys developers
Maintainer-email: pyansys.maintainers@ansys.com
License: MIT
Keywords: vtk MAPDL ANSYS cdb full rst
Classifier: Development Status :: 4 - Beta
Classifier: Intended Audience :: Science/Research
Classifier: Topic :: Scientific/Engineering :: Information Analysis
Classifier: License :: OSI Approved :: MIT License
Classifier: Operating System :: Microsoft :: Windows
Classifier: Operating System :: POSIX
Classifier: Operating System :: MacOS
Classifier: Programming Language :: Python :: 3.10
Classifier: Programming Language :: Python :: 3.11
Classifier: Programming Language :: Python :: 3.12
Classifier: Programming Language :: Python :: 3.13
Requires-Python: >=3.10,<4
License-File: LICENSE
License-File: AUTHORS
Requires-Dist: appdirs>=1.4.0
Requires-Dist: matplotlib>=3.0.0
Requires-Dist: numpy<3,>=1.16.0
Requires-Dist: pyvista>=0.32.0
Requires-Dist: tqdm>=4.45.0
Requires-Dist: vtk<10,>=9.0.0
Dynamic: author
Dynamic: author-email
Dynamic: classifier
Dynamic: description
Dynamic: description-content-type
Dynamic: home-page
Dynamic: keywords
Dynamic: license
Dynamic: license-file
Dynamic: maintainer
Dynamic: maintainer-email
Dynamic: requires-dist
Dynamic: requires-python
Dynamic: summary
